{"version":1,"resource":"file:///home/edzonag/Documents/tareaPulga/ecuaciones.tex","entries":[{"id":"W4jX.tex","timestamp":1665648412818},{"id":"aOqp.tex","timestamp":1665648475377},{"id":"stDY.tex","timestamp":1665648538273},{"id":"IM5g.tex","timestamp":1665648623306},{"id":"RpuG.tex","timestamp":1665648681022},{"id":"lSQg.tex","timestamp":1665648836122},{"id":"HlTk.tex","timestamp":1665649024983},{"id":"Lwi6.tex","timestamp":1665649042023},{"id":"C3Xv.tex","timestamp":1665650455184},{"id":"haCZ.tex","timestamp":1665650546538},{"id":"bnFv.tex","timestamp":1665651367508},{"id":"Uby5.tex","timestamp":1665652276639},{"id":"a7tK.tex","timestamp":1665652311154},{"id":"n4JO.tex","timestamp":1665652659247},{"id":"u9y0.tex","timestamp":1665652824621}]}